piholesdk/__init__.py
piholesdk/piholesdk.py
tests/__init__.py
tests/test_piholesdk.py
piholesdk-0.1.3.dist-info/METADATA
piholesdk-0.1.3.dist-info/WHEEL
piholesdk-0.1.3.dist-info/top_level.txt
piholesdk-0.1.3.dist-info/RECORD
