Metadata-Version: 2.1
Name: piholesdk
Version: 0.1.3
Summary: A Python client for managing DNS records on a Pi-hole server via SSH.
Home-page: https://github.com/melihteke/piholesdk.git
Author: Melih Teke
Author-email: me@mteke.com
Classifier: Programming Language :: Python :: 3
Classifier: License :: OSI Approved :: MIT License
Classifier: Operating System :: OS Independent
Requires-Python: >=3.6
Requires-Dist: paramiko
